picsumphotos/__init__.py
picsumphotos/picsumphotos.py
picsumphotos-1.0.1.dist-info/LICENSE
picsumphotos-1.0.1.dist-info/METADATA
picsumphotos-1.0.1.dist-info/WHEEL
picsumphotos-1.0.1.dist-info/top_level.txt
picsumphotos-1.0.1.dist-info/RECORD
