Metadata-Version: 2.1
Name: picsumphotos
Version: 1.0.1
Summary: A package for image processing utilities using the Picsum API
Home-page: https://escapedshadows.com/pythonlibs/picsumphotos.html
Author: EscapedShadows
Author-email: packages@escapedshadows.com
Classifier: Programming Language :: Python :: 3
Classifier: License :: OSI Approved :: Apache Software License
Classifier: Operating System :: OS Independent
Requires-Python: >=3.6
License-File: LICENSE
Requires-Dist: requests
Requires-Dist: urllib3
